haoqiren_py/__init__.py
haoqiren_py/base/__init__.py
haoqiren_py/base/datetime.py
haoqiren_py/base/path.py
haoqiren_py/base/platform.py
haoqiren_py/io/__init__.py
haoqiren_py/io/directory.py
haoqiren_py/io/file.py
haoqiren_py/io/path.py
haoqiren_py/math/__init__.py
haoqiren_py/math/prime.py
haoqiren_py/net/__init__.py
haoqiren_py/office/__init__.py
haoqiren_py/office/excel/__init__.py
haoqiren_py/office/excel/openpyxl/__init__.py
haoqiren_py/office/excel/openpyxl/excel.py
haoqiren_py/office/excel/xlrw/__init__.py
haoqiren_py/office/excel/xlsxwriter/__init__.py
haoqiren_py/office/excel/xlutils/__init__.py
haoqiren_py/office/word/__init__.py
haoqiren_py/office/word/pydocx/__init__.py
haoqiren_py/office/word/pydocx/document.py
haoqiren_py/ui/__init__.py
haoqiren_py/ui/tkinter/__init__.py
haoqiren_py/ui/tkinter/form.py
haoqiren_py/ui/tkinter/tkinterhelper.py
haoqiren-0.0.1.dist-info/METADATA
haoqiren-0.0.1.dist-info/WHEEL
haoqiren-0.0.1.dist-info/top_level.txt
haoqiren-0.0.1.dist-info/RECORD
